ep/__init__.py
ep/cli.py
ep/compat.py
ep/env.py
ep/main.py
ep/npm.py
ep/package.py
ep/python.py
ep/shell.py
ep/version.py
ep-0.2.4.dist-info/DESCRIPTION.rst
ep-0.2.4.dist-info/entry_points.txt
ep-0.2.4.dist-info/METADATA
ep-0.2.4.dist-info/metadata.json
ep-0.2.4.dist-info/pbr.json
ep-0.2.4.dist-info/RECORD
ep-0.2.4.dist-info/top_level.txt
ep-0.2.4.dist-info/WHEEL
