Metadata-Version: 2.0
Name: ep
Version: 0.2.4
Summary: A tool to support an explicit contract between application and plaftorm
Home-page: https://github.com/txels/ep
Author: Carles Barrobés
Author-email: carles@barrobes.com
License: UNKNOWN
Platform: UNKNOWN
Classifier: Environment :: Console
Classifier: Intended Audience :: Developers
Classifier: Programming Language :: Python
Classifier: Programming Language :: Python :: 2
Classifier: Programming Language :: Python :: 2.6
Classifier: Programming Language :: Python :: 2.7
Classifier: Programming Language :: Python :: 3
Classifier: Programming Language :: Python :: 3.2
Classifier: Programming Language :: Python :: 3.3
Classifier: Programming Language :: Python :: 3.4
Classifier: Topic :: Software Development :: Build Tools
Classifier: Topic :: Software Development :: Libraries
Requires-Dist: PyYAML (==3.11)
Requires-Dist: docopt (==0.6.2)
Requires-Dist: semver (==2.0.2)
Requires-Dist: wheel (==0.24.0)
